probabilistic_automata/__init__.py
probabilistic_automata/distributions.py
probabilistic_automata/markov_chain.py
probabilistic_automata/pa.py
probabilistic_automata/utils.py
probabilistic_automata-0.4.2.dist-info/LICENSE
probabilistic_automata-0.4.2.dist-info/WHEEL
probabilistic_automata-0.4.2.dist-info/METADATA
probabilistic_automata-0.4.2.dist-info/RECORD
