Metadata-Version: 2.1
Name: probabilistic-automata
Version: 0.4.2
Summary: Python library for manipulating probabilistic automata.
Home-page: https://github.com/mvcisback/probabilistic_automata
License: MIT
Author: Marcell Vazquez-Chanlatte
Author-email: mvc@linux.com
Requires-Python: >=3.7,<4.0
Classifier: License :: OSI Approved :: MIT License
Classifier: Programming Language :: Python :: 3
Classifier: Programming Language :: Python :: 3.7
Classifier: Programming Language :: Python :: 3.8
Requires-Dist: attrs (>=20.0.0,<21.0.0)
Requires-Dist: dfa (>=2.1.0,<3.0.0)
Requires-Dist: funcy (>=1.14,<2.0)
Requires-Dist: lenses (>=0.5.0,<0.6.0)
Project-URL: Repository, https://github.com/mvcisback/probabilistic_automata
